keyword_generator/__init__.py
keyword_generator/claude_client.py
keyword_generator/main.py
keyword_generator/cli/__init__.py
keyword_generator/cli/commands.py
keyword_generator/cli/ui.py
keyword_generator/core/__init__.py
keyword_generator/pdf/__init__.py
keyword_generator/pdf/reader.py
keyword_generator/pdf/writer.py
keyword_generator/utils/__init__.py
keyword_generator/utils/error_handlers.py
keyword_generator/utils/exceptions.py
keyword_generator/utils/result_types.py
resume_keyword_injector-1.0.1.dist-info/METADATA
resume_keyword_injector-1.0.1.dist-info/WHEEL
resume_keyword_injector-1.0.1.dist-info/entry_points.txt
resume_keyword_injector-1.0.1.dist-info/licenses/LICENSE
resume_keyword_injector-1.0.1.dist-info/RECORD
