Metadata-Version: 2.4
Name: resume-keyword-injector
Version: 1.0.1
Summary: Add invisible ATS-friendly keywords to PDF resumes
Project-URL: Homepage, https://github.com/SimonOneNineEight/resume-keyword-injector
Project-URL: Repository, https://github.com/SimonOneNineEight/resume-keyword-injector
License: MIT License
License-File: LICENSE
Keywords: ats,job-search,keyword,optimization,pdf,python,resume
Classifier: Development Status :: 5 - Production/Stable
Classifier: Environment :: Console
Classifier: Intended Audience :: End Users/Desktop
Classifier: License :: OSI Approved :: MIT License
Classifier: Programming Language :: Python :: 3
Classifier: Programming Language :: Python :: 3.11
Classifier: Topic :: Office/Business
Classifier: Topic :: Utilities
Requires-Python: >=3.11
Requires-Dist: click>=8.2.1
Requires-Dist: pdfplumber>=0.9.0
Requires-Dist: pypdf>=3.0.0
Requires-Dist: reportlab>=4.0.0
Requires-Dist: rich>=14.0.0
Provides-Extra: dev
Requires-Dist: pytest>=7.0.0; extra == 'dev'
